{"nodes": [{"id": "fluentic_ai_concept", "label": "Fluentic AI", "file_type": "concept", "source_file": "fluentic-ai-backup-2026-05-06/README.md"}, {"id": "gemini_2_0_flash_entity", "label": "Google Gemini 2.0 Flash", "file_type": "code", "source_file": "fluentic-ai-backup-2026-05-06/README.md"}], "edges": [{"source": "fluentic_ai_concept", "target": "gemini_2_0_flash_entity", "relation": "calls", "confidence": "EXTRACTED", "confidence_score": 1.0, "source_file": "fluentic-ai-backup-2026-05-06/README.md"}], "hyperedges": []}